climt-0.17.13.dist-info/LICENSE
climt-0.17.13.dist-info/top_level.txt
climt-0.17.13.dist-info/METADATA
climt-0.17.13.dist-info/WHEEL
climt-0.17.13.dist-info/AUTHORS.rst
climt-0.17.13.dist-info/RECORD
climt.libs/libgfortran-040039e1.so.5.0.0
climt.libs/libquadmath-96973f99.so.0.0.0
climt.libs/libgomp-a34b3233.so.1.0.0
climt/__init__.py
climt/_lib/Makefile
climt/_lib/Darwin/.temp
climt/_lib/simple_physics/Makefile
climt/_lib/simple_physics/simple_physics_custom.f90
climt/_lib/simple_physics/simple_physics_v5_1.f90
climt/_lib/rrtmg_sw/rrsw_ref.f90
climt/_lib/rrtmg_sw/rrsw_con.f90
climt/_lib/rrtmg_sw/rrtmg_sw_init.f90
climt/_lib/rrtmg_sw/rrtmg_sw_rad.nomcica.f90
climt/_lib/rrtmg_sw/rrsw_cld.f90
climt/_lib/rrtmg_sw/rrsw_kg19.f90
climt/_lib/rrtmg_sw/mcica_random_numbers.f90
climt/_lib/rrtmg_sw/parkind.f90
climt/_lib/rrtmg_sw/Makefile
climt/_lib/rrtmg_sw/rrtmg_sw_cldprop.f90
climt/_lib/rrtmg_sw/rrsw_kg26.f90
climt/_lib/rrtmg_sw/rrsw_tbl.f90
climt/_lib/rrtmg_sw/rrtmg_sw_c_binder.f90
climt/_lib/rrtmg_sw/rrsw_kg20.f90
climt/_lib/rrtmg_sw/rrtmg_sw_spcvrt.f90
climt/_lib/rrtmg_sw/rrsw_kg17.f90
climt/_lib/rrtmg_sw/rrtmg_sw_taumol.f90
climt/_lib/rrtmg_sw/rrsw_aer.f90
climt/_lib/rrtmg_sw/rrtmg_sw_cldprmc.f90
climt/_lib/rrtmg_sw/rrsw_kg22.f90
climt/_lib/rrtmg_sw/rrsw_kg29.f90
climt/_lib/rrtmg_sw/rrtmg_sw_spcvmc.f90
climt/_lib/rrtmg_sw/README
climt/_lib/rrtmg_sw/rrtmg_sw_setcoef.f90
climt/_lib/rrtmg_sw/rrsw_kg23.f90
climt/_lib/rrtmg_sw/rrsw_ncpar.f90
climt/_lib/rrtmg_sw/rrtmg_sw_k_g.f90
climt/_lib/rrtmg_sw/rrtmg_sw_rad.f90
climt/_lib/rrtmg_sw/mcica_subcol_gen_sw.f90
climt/_lib/rrtmg_sw/parrrsw.f90
climt/_lib/rrtmg_sw/rrsw_kg18.f90
climt/_lib/rrtmg_sw/rrsw_kg21.f90
climt/_lib/rrtmg_sw/rrsw_kg27.f90
climt/_lib/rrtmg_sw/rrsw_kg24.f90
climt/_lib/rrtmg_sw/rrsw_kg16.f90
climt/_lib/rrtmg_sw/setup.py
climt/_lib/rrtmg_sw/rrtmg_sw_vrtqdr.f90
climt/_lib/rrtmg_sw/rrsw_vsn.f90
climt/_lib/rrtmg_sw/rrtmg_sw_reftra.f90
climt/_lib/rrtmg_sw/rrsw_kg28.f90
climt/_lib/rrtmg_sw/rrsw_wvn.f90
climt/_lib/rrtmg_sw/rrsw_kg25.f90
climt/_lib/Linux/.temp
climt/_lib/rrtmg_lw/rrlw_ncpar.f90
climt/_lib/rrtmg_lw/rrtmg_lw_rad.nomcica.f90
