Metadata-Version: 2.1
Name: climt
Version: 0.17.13
Summary: CliMT is a Toolkit for building Earth system models in Python.
Home-page: https://github.com/CliMT/climt
Author: Rodrigo Caballero
Author-email: rodrigo.caballero@misu.su.se
License: BSD license
Keywords: climt
Classifier: Development Status :: 2 - Pre-Alpha
Classifier: Intended Audience :: Developers
Classifier: License :: OSI Approved :: BSD License
Classifier: Natural Language :: English
Classifier: Programming Language :: Python :: 2
Classifier: Programming Language :: Python :: 2.7
Classifier: Programming Language :: Python :: 3
Classifier: Programming Language :: Python :: 3.4
Classifier: Programming Language :: Python :: 3.5
Classifier: Programming Language :: Python :: 3.6
License-File: LICENSE
License-File: AUTHORS.rst
Requires-Dist: numpy (>=1.16.0)
Requires-Dist: pint (>=0.7.0)
Requires-Dist: xarray (>=0.8.0)
Requires-Dist: sympl (==0.4.1)
Requires-Dist: cython (>=0.25)
Requires-Dist: scipy (>=0.18.1)
